x_python-1.5.3.dist-info/licenses/AUTHORS
x_python-1.5.3.dist-info/licenses/LICENSE
xpython/.gitignore
xpython/__init__.py
xpython/__main__.py
xpython/builtins.py
xpython/execfile.py
xpython/pyobj.py
xpython/version.py
xpython/version_info.py
xpython/vm.py
xpython/vmtrace.py
xpython/byteop/.gitignore
xpython/byteop/__init__.py
xpython/byteop/byteop.py
xpython/byteop/byteop24.py
xpython/byteop/byteop25.py
xpython/byteop/byteop26.py
xpython/byteop/byteop26pypy.py
xpython/byteop/byteop27.py
xpython/byteop/byteop27pypy.py
xpython/byteop/byteop31.py
xpython/byteop/byteop310.py
xpython/byteop/byteop311.py
xpython/byteop/byteop312.py
xpython/byteop/byteop32.py
xpython/byteop/byteop32pypy.py
xpython/byteop/byteop33.py
xpython/byteop/byteop34.py
xpython/byteop/byteop35.py
xpython/byteop/byteop35pypy.py
xpython/byteop/byteop36.py
xpython/byteop/byteop36pypy.py
xpython/byteop/byteop37.py
xpython/byteop/byteop37pypy.py
xpython/byteop/byteop38.py
xpython/byteop/byteop38pypy.py
xpython/byteop/byteop39.py
xpython/byteop/byteop39pypy.py
xpython/byteop/byteoppypy.py
xpython/interpreter/baseobjspace.py
xpython/interpreter/error.py
xpython/interpreter/generator.py
xpython/interpreter/pyopcode.py
xpython/stdlib/__init__.py
xpython/stdlib/builtins.py
xpython/stdlib/builtins_24.py
xpython/stdlib/builtins_25.py
xpython/stdlib/builtins_26.py
xpython/stdlib/builtins_27.py
xpython/stdlib/builtins_31.py
xpython/stdlib/builtins_32.py
xpython/stdlib/builtins_33.py
xpython/stdlib/builtins_36.py
xpython/stdlib/builtins_38.py
xpython/stdlib/inspect2.py
xpython/stdlib/inspect3.py
xpython/stdlib/inspectfor32.py
xpython/stdlib/itertools_compat.py
xpython/stdlib/types34.py
x_python-1.5.3.dist-info/METADATA
x_python-1.5.3.dist-info/WHEEL
x_python-1.5.3.dist-info/entry_points.txt
x_python-1.5.3.dist-info/top_level.txt
x_python-1.5.3.dist-info/RECORD
