Metadata-Version: 2.4
Name: x-python
Version: 1.5.3
Summary: Python cross-version byte-code interpeter
Author: Ned Batchelder, Paul Swartz
Author-email: Rocky Bernstein <rb@dustyfeet.com>
License-Expression: MIT
Project-URL: Homepage, https://pypi.org/project/x-python/
Project-URL: Downloads, https://github.com/rocky/x-python/releases
Keywords: Python bytecode,bytecode,disassembler
Classifier: Intended Audience :: Developers
Classifier: Operating System :: OS Independent
Classifier: Programming Language :: Python
Classifier: Programming Language :: Python :: 2.7
Classifier: Programming Language :: Python :: 3.1
Classifier: Programming Language :: Python :: 3.2
Classifier: Programming Language :: Python :: 3.3
Classifier: Programming Language :: Python :: 3.4
Classifier: Programming Language :: Python :: 3.5
Classifier: Programming Language :: Python :: 3.6
Classifier: Programming Language :: Python :: 3.7
Classifier: Programming Language :: Python :: 3.8
Classifier: Programming Language :: Python :: 3.9
Classifier: Programming Language :: Python :: 3.10
Classifier: Programming Language :: Python :: 3.11
Classifier: Programming Language :: Python :: 3.12
Classifier: Programming Language :: Python :: 3.13
Classifier: Programming Language :: Python :: Implementation :: PyPy
License-File: LICENSE
License-File: AUTHORS
Requires-Dist: click
Requires-Dist: xdis<6.3,>=6.0.3
Provides-Extra: dev
Requires-Dist: flake8; extra == "dev"
Requires-Dist: pre-commit; extra == "dev"
Requires-Dist: pytest; extra == "dev"
Dynamic: license-file
